opensees/README.md
opensees/__init__.py
opensees/__main__.py
opensees/_invoke.py
opensees/analysis.py
opensees/libOpenSeesRT.so
opensees/openseespy.py
opensees/openseespy.pyi
opensees/recorder.py
opensees/series.py
opensees/tcl.py
opensees/emit/__init__.py
opensees/emit/__main__.py
opensees/emit/apidoc.py
opensees/emit/emit_json.py
opensees/emit/emitter.py
opensees/emit/fedeas.py
opensees/emit/mesh.py
opensees/emit/opensees.py
opensees/emit/registry.py
opensees/emit/writer.py
opensees/library/__init__.py
opensees/library/ast.py
opensees/library/frame.py
opensees/library/material.py
opensees/library/model.py
opensees/library/obj.py
opensees/library/pattern.py
opensees/library/shell.py
opensees/library/solid.py
opensees/repl/__init__.py
opensees/repl/cmdshell.py
opensees/repl/ptkshell.py
opensees/repl/unix.py
opensees/section/__init__.py
opensees/section/aisc_imperial.py
opensees/section/patch.py
opensees/section/section.py
opensees/section/shapes.py
opensees/units/__init__.py
opensees/units/__main__.py
opensees/units/cgs.py
opensees/units/english.py
opensees/units/fas.py
opensees/units/fks.py
opensees/units/fps.py
opensees/units/ias.py
opensees/units/iks.py
opensees/units/ips.py
opensees/units/mks.py
opensees/units/si.py
opensees/units/units.py
opensees.libs/libgfortran-040039e1.so.5.0.0
opensees.libs/libgfortran-91cc3cb1.so.3.0.0
opensees.libs/libgomp-a34b3233.so.1.0.0
opensees.libs/libopenblas-r0-f650aae0.3.3.so
opensees.libs/libquadmath-96973f99.so.0.0.0
opensees-0.1.27.dist-info/METADATA
opensees-0.1.27.dist-info/WHEEL
opensees-0.1.27.dist-info/entry_points.txt
opensees-0.1.27.dist-info/top_level.txt
opensees-0.1.27.dist-info/RECORD
opensees-0.1.27.dist-info/licenses/LICENSE.txt
