Metadata-Version: 2.4
Name: opensees
Version: 0.1.27
Summary: Nonlinear finite element analysis.
Project-URL: Repository, https://github.com/peer-open-source/xara
Project-URL: Documentation, https://xara.so
Project-URL: Examples, https://gallery.stairlab.io
Keywords: computational-mechanics,structural-engineering,finite-element-analysis,earthquake,engineering,xara
Classifier: Development Status :: 5 - Production/Stable
Classifier: Intended Audience :: Science/Research
Classifier: Intended Audience :: Developers
Classifier: Programming Language :: C
Classifier: Programming Language :: C++
Classifier: Programming Language :: Fortran
Classifier: Programming Language :: Python
Classifier: Programming Language :: Python :: 3
Classifier: Programming Language :: Python :: 3.8
Classifier: Programming Language :: Python :: 3.9
Classifier: Programming Language :: Python :: 3.10
Classifier: Programming Language :: Python :: 3.11
Classifier: Programming Language :: Python :: 3.12
Classifier: Programming Language :: Python :: 3 :: Only
Classifier: Topic :: Software Development
Classifier: Topic :: Scientific/Engineering
Classifier: Operating System :: Microsoft :: Windows
Classifier: Operating System :: POSIX
Classifier: Operating System :: Unix
Classifier: Operating System :: MacOS
License-File: LICENSE.txt
Requires-Dist: shps>=0.0.14
Requires-Dist: numpy<1.20.0; python_version < "3.8"
Requires-Dist: numpy; python_version >= "3.8"
Requires-Dist: tcinter>=1.0; platform_python_implementation == "PyPy" or sys_platform == "emscripten"
Requires-Dist: mkl; sys_platform == "win32"
Requires-Dist: intel-fortran-rt; sys_platform == "win32"
Requires-Dist: prompt_toolkit
Requires-Dist: platformdirs
Provides-Extra: tcl
Requires-Dist: tcinter>=0.6; extra == "tcl"
Dynamic: license-file
